setup.py
base_utils/__init__.py
base_utils/cache.py
base_utils/db.py
base_utils/des.py
base_utils/logger.py
base_utils/rsa.py
base_utils/statistic.py
base_utils/util.py
base_utils.egg-info/PKG-INFO
base_utils.egg-info/SOURCES.txt
base_utils.egg-info/dependency_links.txt
base_utils.egg-info/requires.txt
base_utils.egg-info/top_level.txt
test/test_logger.py