Metadata-Version: 1.0
Name: base-utils
Version: 1.0.14
Summary: utils
Home-page: http://www.xxx.cc
Author: UNKNOWN
Author-email: nicajonh@gmail.com
License: UNKNOWN
Platform: UNKNOWN
